deezapileaks/__init__.py
deezapileaks/main.py
deezapileaks-1.0.dist-info/LICENSE
deezapileaks-1.0.dist-info/METADATA
deezapileaks-1.0.dist-info/WHEEL
deezapileaks-1.0.dist-info/top_level.txt
deezapileaks-1.0.dist-info/RECORD
